Workbook
Name AvoidFuelCost: EBCA!$B$12
Name CapitalCost: EBCA!$B$24
Name CO2Avoided: EBCA!$B$9
Name DiscountedEPBP: EBCA!$C$85
Name DiscountedPBP: [1]FBCA!$C$57
Name DiscountRate: EBCA!$B$5
Name EBCR: EBCA!$C$83
Name EfficiencyDerate: EBCA!$B$14
Name EIRR: EBCA!$C$84
Name EmpIncomePerJob: EBCA!$B$19
Name EmpJobsAfteryr0: EBCA!$B$17
Name EmpJobsForyr0: EBCA!$B$18
Name ENPV: EBCA!$C$82
Name EnvBenifit: EBCA!$B$11
Name EnvImpactCostyr0: EBCA!$B$21
Name FBCR: [1]FBCA!$C$55
Name FIRR: [1]FBCA!$C$56
Name FNPV: [1]FBCA!$C$54
Name Generation: EBCA!$B$13
Name LossOfRoyaltyRevenue: EBCA!$B$20
Name ModuleDegradation: EBCA!$B$16
Name OandMescalation: EBCA!$B$22
Name OandMyr1: EBCA!$B$23
Name ShadowExchRateFact: EBCA!$B$8
Name ShadWageRateFac: EBCA!$B$7
Name SimpleEPBP: EBCA!$C$86
Name SocialCostOfCarbon: EBCA!$B$10
Name StandConvFact: EBCA!$B$6
Name Tariff: EBCA!$B$15

Sheet EBCA
A1: Economic Benefit - Cost Analysis (EBCA) – Siyambalanduwa 100 MW Solar
A3: 1. Assumptions & Parameters
A5: Economic discount rate (real) | B5: =Sensitivity_Analysis!C5 -> 0.09
A6: Standard Conversion Factor (SCF) | B6: =Sensitivity_Analysis!C6 -> 0.9
A7: Shadow Wage Rate Factor (SWRF) | B7: =Sensitivity_Analysis!C7 -> 0.8
A8: Shadow Exchange Rate Factor (SERF) | B8: =Sensitivity_Analysis!C8 -> 1.1
A9: CO₂ avoided (ton/year) | B9: 147582
A10: Social cost of carbon (LKR/ton) | B10: =Sensitivity_Analysis!C9 -> 10000
A11: Environmental benefit (LKR mn/year) | B11: =B9*B10/1000000 -> 1475.82
A12: Avoided fuel cost (LKR/kWh) | B12: =Sensitivity_Analysis!C10 -> 19
A13: Annual generation (GWh) (Year 1) | B13: =Sensitivity_Analysis!C11 -> 180
A14: Efficiency derate (Performance Ratio) | B14: 0.85
A15: Tariff (LKR/kWh) | B15: 14
A16: Module degradation (per year) | B16: 0.007
A17: Employment (jobs) after year 0 | B17: =Sensitivity_Analysis!C12 -> 100
A18: Employment (jobs) for year 0 | B18: =Sensitivity_Analysis!C13 -> 1000
A19: Employment income per job (LKR mn/yr) | B19: =Sensitivity_Analysis!C14 -> 1
A20: Loss of royalty revenue (LKR mn/yr) | B20: =Sensitivity_Analysis!C15 -> 15
A21: Environmental impact cost Year 0 (LKR mn) | B21: =Sensitivity_Analysis!C16 -> 30
A22: O&M escalation (per year) | B22: =Sensitivity_Analysis!C17 -> 0.05
A23: O&M % of CapEx (financial) Year 1 | B23: =Sensitivity_Analysis!C18 -> 0.01
A24: CAPEX total (financial, LKR mn) | B24: =Sensitivity_Analysis!C19 -> 14833.65
A26: 2. Conversion of Financial Costs to Economic Costs
A28: Item | B28: Financial | C28: Split | D28: Conv | E28: Economic
A29: CAPEX
A30: Foreign component | B30: =B24 -> 14833.65 | C30: 0.6 | D30: =B8 -> 1.1 | E30: =B30*C30*D30 -> 9790.209
A31: Local goods/services | B31: =B24 -> 14833.65 | C31: 0.3 | D31: =B6 -> 0.9 | E31: =B31*C31*D31 -> 4005.0855
A32: Local labour | B32: =B24 -> 14833.65 | C32: 0.1 | D32: =B7 -> 0.8 | E32: =B32*C32*D32 -> 1186.692
A33: Total CAPEX (Economic) | E33: =SUM(E30:E32) -> 14981.986
A34: O&M
A35: Foreign content (yr 1) | B35: =B$24*B$23 -> 148.3365 | C35: 0.2 | D35: =B8 -> 1.1 | E35: =B35*C35*D35 -> 32.63403
A36: Local goods (yr 1) | B36: =B$24*B$23 -> 148.3365 | C36: 0.5 | D36: =B6 -> 0.9 | E36: =B36*C36*D36 -> 66.751425
A37: Local labour (yr 1) | B37: =B$24*B$23 -> 148.3365 | C37: 0.3 | D37: =B7 -> 0.8 | E37: =B37*C37*D37 -> 35.60076
A38: Total O&M (Economic, yr 1) | E38: =SUM(E35:E37) -> 134.98622
A40: 3. Economic Cash Flow Analysis
A42: Year | B42: Total | C42: 0 | D42: 1 | E42: 2 | F42: 3 | G42: 4 | H42: 5 | I42: 6 | J42: 7 | K42: 8 | L42: 9 | M42: 10 | N42: 11 | O42: 12 | P42: 13 | Q42: 14 | R42: 15 | S42: 16 | T42: 17 | U42: 18 | V42: 19 | W42: 20
A43: Energy (GWh) | B43: =SUM(C43:W43) -> 3370.3623 | C43: 0 | D43: =B13 -> 180 | E43: =D43*(1-$B$16) -> 178.74 | F43: =E43*(1-$B$16) -> 177.48882 | G43: =F43*(1-$B$16) -> 176.2464 | H43: =G43*(1-$B$16) -> 175.01267 | I43: =H43*(1-$B$16) -> 173.78758 | J43: =I43*(1-$B$16) -> 172.57107 | K43: =J43*(1-$B$16) -> 171.36307 | L43: =K43*(1-$B$16) -> 170.16353 | ... W43: =V43*(1-$B$16) -> 157.51003
A44: Economic Benefit
A45: Tariff revenue (LKR mn) | B45: =SUM(C45:W45) -> 40107.311 | C45: 0 | D45: =$B$13*((1-$B$16)^(D42-1))*$B$14*$B$15 -> 2142 | E45: =$B$13*((1-$B$16)^(E42-1))*$B$14*$B$15 -> 2127.006 | F45: =$B$13*((1-$B$16)^(F42-1))*$B$14*$B$15 -> 2112.117 | G45: =$B$13*((1-$B$16)^(G42-1))*$B$14*$B$15 -> 2097.3321 | H45: =$B$13*((1-$B$16)^(H42-1))*$B$14*$B$15 -> 2082.6508 | I45: =$B$13*((1-$B$16)^(I42-1))*$B$14*$B$15 -> 2068.0723 | J45: =$B$13*((1-$B$16)^(J42-1))*$B$14*$B$15 -> 2053.5958 | K45: =$B$13*((1-$B$16)^(K42-1))*$B$14*$B$15 -> 2039.2206 | ... W45: =$B$13*((1-$B$16)^(W42-1))*$B$14*$B$15 -> 1874.3694
A46: Avoided Fuel (LKR mn) | B46: =SUM(C46:W46) -> 64036.883 | C46: =C43*$B$12 -> 0 | D46: =D43*$B$12 -> 3420 | E46: =E43*$B$12 -> 3396.06 | F46: =F43*$B$12 -> 3372.2876 | G46: =G43*$B$12 -> 3348.6816 | H46: =H43*$B$12 -> 3325.2408 | I46: =I43*$B$12 -> 3301.9641 | J46: =J43*$B$12 -> 3278.8504 | ... W46: =W43*$B$12 -> 2992.6907
A47: CO₂ (LKR mn) | B47: =SUM(C47:W47) -> 29516.4 | C47: =IF(C42=0,0,$B$11) -> 0 | D47: =IF(D42=0,0,$B$11) -> 1475.82 | E47: =IF(E42=0,0,$B$11) -> 1475.82 | F47: =IF(F42=0,0,$B$11) -> 1475.82 | G47: =IF(G42=0,0,$B$11) -> 1475.82 | H47: =IF(H42=0,0,$B$11) -> 1475.82 | I47: =IF(I42=0,0,$B$11) -> 1475.82 | J47: =IF(J42=0,0,$B$11) -> 1475.82 | ... W47: =IF(W42=0,0,$B$11) -> 1475.82
A48: Employment (LKR mn) | B48: =SUM(C48:W48) -> 3000 | C48: =IF(C42=0,$B$18*$B$19,$B$17*$B$19) -> 1000 | D48: =IF(D42=0,0,$B$17*$B$19) -> 100 | E48: =IF(E42=0,0,$B$17*$B$19) -> 100 | F48: =IF(F42=0,0,$B$17*$B$19) -> 100 | G48: =IF(G42=0,0,$B$17*$B$19) -> 100 | H48: =IF(H42=0,0,$B$17*$B$19) -> 100 | I48: =IF(I42=0,0,$B$17*$B$19) -> 100 | J48: =IF(J42=0,0,$B$17*$B$19) -> 100 | K48: =IF(K42=0,0,$B$17*$B$19) -> 100 | ... W48: =IF(W42=0,0,$B$17*$B$19) -> 100
A49: Total Economic Benefits (LKR mn) | B49: =SUM(C49:W49) -> 96553.283 | C49: =SUM(C46:C48) -> 1000 | D49: =SUM(D46:D48) -> 4995.82 | E49: =SUM(E46:E48) -> 4971.88 | F49: =SUM(F46:F48) -> 4948.1076 | G49: =SUM(G46:G48) -> 4924.5016 | H49: =SUM(H46:H48) -> 4901.0608 | I49: =SUM(I46:I48) -> 4877.7841 | J49: =SUM(J46:J48) -> 4854.6704 | ... W49: =SUM(W46:W48) -> 4568.5107
A50: Economic costs
A51: CAPEX (LKR mn) | B51: =SUM(C51:W51) -> 14981.986 | C51: =IF(C42=0,$E$33,0) -> 14981.986 | D51: =IF(D42=0,$E$33,0) -> 0 | E51: =IF(E42=0,$E$33,0) -> 0 | F51: =IF(F42=0,$E$33,0) -> 0 | G51: =IF(G42=0,$E$33,0) -> 0 | H51: =IF(H42=0,$E$33,0) -> 0 | I51: =IF(I42=0,$E$33,0) -> 0 | J51: =IF(J42=0,$E$33,0) -> 0 | ... W51: =IF(W42=0,$E$33,0) -> 0
A52: O&M (LKR mn) | B52: =SUM(C52:W52) -> 4463.448 | C52: 0 | D52: =$E$38 -> 134.98622 | E52: =D52*(1+$B$22) -> 141.73553 | F52: =E52*(1+$B$22) -> 148.8223 | G52: =F52*(1+$B$22) -> 156.26342 | H52: =G52*(1+$B$22) -> 164.07659 | I52: =H52*(1+$B$22) -> 172.28042 | J52: =I52*(1+$B$22) -> 180.89444 | K52: =J52*(1+$B$22) -> 189.93916 | L52: =K52*(1+$B$22) -> 199.43612 | ... W52: =V52*(1+$B$22) -> 341.10344
A53: Env. Impact Cost One-time (LKR mn) | B53: =SUM(C53:W53) -> 30 | C53: =IF(C42=0,$B$21,0) -> 30 | D53: =IF(D42=0,$B$21,0) -> 0 | E53: =IF(E42=0,$B$21,0) -> 0 | F53: =IF(F42=0,$B$21,0) -> 0 | G53: =IF(G42=0,$B$21,0) -> 0 | H53: =IF(H42=0,$B$21,0) -> 0 | I53: =IF(I42=0,$B$21,0) -> 0 | J53: =IF(J42=0,$B$21,0) -> 0 | ... W53: =IF(W42=0,$B$21,0) -> 0
A54: Other / Royalty (LKR mn) | B54: =SUM(C54:W54) -> 300 | C54: =IF(C42=0,0,$B$20) -> 0 | D54: =IF(D42=0,0,$B$20) -> 15 | E54: =IF(E42=0,0,$B$20) -> 15 | F54: =IF(F42=0,0,$B$20) -> 15 | G54: =IF(G42=0,0,$B$20) -> 15 | H54: =IF(H42=0,0,$B$20) -> 15 | I54: =IF(I42=0,0,$B$20) -> 15 | J54: =IF(J42=0,0,$B$20) -> 15 | ... W54: =IF(W42=0,0,$B$20) -> 15
A55: Total Economic Costs (LKR mn) | B55: =SUM(C55:W55) -> 19475.434 | C55: =SUM(C51:C53) -> 15011.986 | D55: =SUM(D51:D53) -> 134.98622 | E55: =SUM(E51:E53) -> 141.73553 | F55: =SUM(F51:F53) -> 148.8223 | G55: =SUM(G51:G53) -> 156.26342 | H55: =SUM(H51:H53) -> 164.07659 | I55: =SUM(I51:I53) -> 172.28042 | J55: =SUM(J51:J53) -> 180.89444 | ... W55: =SUM(W51:W53) -> 341.10344
A57: Net Economic Flow (LKR mn) | B57: =SUM(C57:W57) -> 77077.848 | C57: =C49-C55 -> -14011.986 | D57: =D49-D55 -> 4860.8338 | E57: =E49-E55 -> 4830.1445 | F57: =F49-F55 -> 4799.2853 | G57: =G49-G55 -> 4768.2381 | H57: =H49-H55 -> 4736.9842 | I57: =I49-I55 -> 4705.5037 | J57: =J49-J55 -> 4673.7759 | ... W57: =W49-W55 -> 4227.4072
A59: 4.Present Value Calculations
A61: EPV of Benefits | C61: =C49/(1+$B$5)^C42 -> 1000 | D61: =D49/(1+$B$5)^D42 -> 4583.3211 | E61: =E49/(1+$B$5)^E42 -> 4184.7319 | F61: =F49/(1+$B$5)^F42 -> 3820.8469 | G61: =G49/(1+$B$5)^G42 -> 3488.6411 | H61: =H49/(1+$B$5)^H42 -> 3185.3532 | I61: =I49/(1+$B$5)^I42 -> 2908.4633 | J61: =J49/(1+$B$5)^J42 -> 2655.6709 | ... W61: =W49/(1+$B$5)^W42 -> 815.16342
A62: EPV of Costs | C62: =C55/(1+$B$5)^C42 -> 15011.986 | D62: =D55/(1+$B$5)^D42 -> 123.84056 | E62: =E55/(1+$B$5)^E42 -> 119.29596 | F62: =F55/(1+$B$5)^F42 -> 114.91812 | G62: =G55/(1+$B$5)^G42 -> 110.70094 | H62: =H55/(1+$B$5)^H42 -> 106.63852 | I62: =I55/(1+$B$5)^I42 -> 102.72518 | J62: =J55/(1+$B$5)^J42 -> 98.955452 | ... W62: =W55/(1+$B$5)^W42 -> 60.863391
A63: EPV of Net Benefits (LKR mn) | C63: =C57/(1+$B$5)^C42 -> -14011.986 | D63: =D57/(1+$B$5)^D42 -> 4459.4805 | E63: =E57/(1+$B$5)^E42 -> 4065.436 | F63: =F57/(1+$B$5)^F42 -> 3705.9288 | G63: =G57/(1+$B$5)^G42 -> 3377.9401 | H63: =H57/(1+$B$5)^H42 -> 3078.7147 | I63: =I57/(1+$B$5)^I42 -> 2805.7381 | J63: =J57/(1+$B$5)^J42 -> 2556.7155 | ... W63: =W57/(1+$B$5)^W42 -> 754.30003
A64: Cumulative EPV Net | C64: =C63 -> -14011.986 | D64: =C64+D63 -> -9552.506 | E64: =D64+E63 -> -5487.07 | F64: =E64+F63 -> -1781.1412 | G64: =F64+G63 -> 1596.7989 | H64: =G64+H63 -> 4675.5136 | I64: =H64+I63 -> 7481.2518 | J64: =I64+J63 -> 10037.967 | K64: =J64+K63 -> 12367.52 | ... W64: =V64+W63 -> 28387.199
A66: 5.Supporting Payback Calculations
A68: Cumulative EPV Net (discounted) | C68: =C64 -> -14011.986 | D68: =D64 -> -9552.506 | E68: =E64 -> -5487.07 | F68: =F64 -> -1781.1412 | G68: =G64 -> 1596.7989 | H68: =H64 -> 4675.5136 | I68: =I64 -> 7481.2518 | J68: =J64 -> 10037.967 | ... W68: =W64 -> 28387.199
A69: Last Negative Year | B69: {=MAX(IF(C68:W68<0,COLUMN(C68:W68)-COLUMN(C68)))} -> 3
A70: Deficit at Last Negative Year | B70: {=INDEX(C68:W68,B69+1)} -> -1781.1412
A71: Next Year Net Benefit | B71: {=INDEX(C68:W68,B69+2)} -> 1596.7989
A72: PBP Index | B72: =B69+ABS(B70)/(ABS(B70)+B71) -> 3.5272862
A74: Cumulative Net (undiscounted) | C74: =C57 -> -14011.986 | D74: =C74+D57 -> -9151.1527 | E74: =D74+E57 -> -4321.0082 | F74: =E74+F57 -> 478.27704 | G74: =F74+G57 -> 5246.5152 | H74: =G74+H57 -> 9983.4994 | I74: =H74+I57 -> 14689.003 | J74: =I74+J57 -> 19362.779 | K74: =J74+K57 -> 24004.558 | ... W74: =V74+W57 -> 77077.848
A75: Last Negative Year | B75: {=MAX(IF(C74:W74<0,COLUMN(C74:W74)-COLUMN(C74)))} -> 2
A76: Deficit at Last Negative Year | B76: {=INDEX(C74:W74,B75+1)} -> -4321.0082
A77: Next Year Net Benefit | B77: {=INDEX(C74:W74,B75+2)} -> 478.27704
A78: Simple PBP Index | B78: =B75+ABS(B76)/(ABS(B76)+B77) -> 2.9003441
A80: 6.Results Summary
A82: ENPV (LKR mn) | C82: =SUM(C63:W63) -> 28387.199
A83: EBCR | C83: =SUM(C61:W61)/SUM(C62:W62) -> 2.6908235
A84: EIRR | C84: =IRR(C57:W57) -> 0.33947035
A85: Discounted Payback Period (years) | C85: =ROUND(B72,2) -> 3.53
A86: Simple Payback Period (years) | C86: =ROUND(B78,2) -> 2.9

Sheet Sensitivity_Analysis
A1: Economic Sensitivity Analysis – Siyambalanduwa 100 MW Solar
A3: Base Case Inputs (Linked to Economic BCA Model)
A5: Economic discount rate (real) | C5: 0.09
A6: Standard Conversion Factor (SCF) | C6: 0.9
A7: Shadow Wage Rate Factor (SWRF) | C7: 0.8
A8: Shadow Exchange Rate Factor (SERF) | C8: 1.1
A9: Social cost of carbon (LKR/ton) | C9: 10000
A10: Avoided fuel cost (LKR/kWh) | C10: 19
A11: Annual generation (GWh) (Year 1) | C11: 180
A12: Employment (jobs) after year 0 | C12: 100
A13: Employment (jobs) for year 0 | C13: 1000
A14: Employment income per job (LKR mn/yr) | C14: 1
A15: Loss of royalty revenue (LKR mn/yr) | C15: 15
A16: Environmental impact cost Year 0 (LKR mn) | C16: 30
... A19: CAPEX total (financial, LKR mn) | C19: 14833.65
A22: (a) Avoided Fuel Cost Sensitivity
A24: Avoided Fuel Cost (LKR/kWh) | B24: ENPV (LKR mn) | C24: EIRR (%) | D24: EPBP (yrs) | E24: EBCR
A25: 19 (Base) | B25: =ENPV -> 28387.199 | C25: =EIRR -> 0.33947035 | D25: =DiscountedEPBP -> 3.53 | E25: =EBCR -> 2.6908235
A26: 15.2 | B26: 22428.952 | C26: 0.28996086 | D26: 4.23 | E26: 2.3359332
A27: 19 | B27: 28387.199 | C27: 0.33947035 | D27: 3.53 | E27: 2.6908235
A28: 22.8 | B28: 34345.445 | C28: 0.38864783 | D28: 3.02 | E28: 3.0457139
A31: (b) Annual Generation Sensitivity
A33: Annual Generation (GWh) | B33: ENPV (LKR mn) | C33: EIRR (%) | D33: EPBP (yrs) | E33: EBCR
A34: 180 (Base) | B34: =ENPV -> 28387.199 | C34: =EIRR -> 0.33947035 | D34: =DiscountedEPBP -> 3.53 | E34: =EBCR -> 2.6908235
A35: 162 | B35: 25408.075 | C35: 0.31477139 | D35: 3.84 | E35: 2.5133783
A36: 180 | B36: 28387.199 | C36: 0.33947035 | D36: 3.53 | E36: 2.6908235
A37: 198 | B37: 31366.322 | C37: 0.36408845 | D37: 3.25 | E37: 2.8682687
A40: (c) CapEx Sensitivity
A42: CapEx (LKR Mn) | B42: ENPV (LKR mn) | C42: EIRR (%) | D42: EPBP (yrs) | E42: EBCR
A43: 14833.65 (Base) | B43: =ENPV -> 28387.199 | C43: =EIRR -> 0.33947035 | D43: =DiscountedEPBP -> 3.53 | E43: =EBCR -> 2.6908235
A44: 12608.603 | B44: 30901.045 | C44: 0.40825618 | D44: 2.86 | E44: 3.1646768
A45: 14833.65 | B45: 28387.199 | C45: 0.33947035 | D45: 3.53 | E45: 2.6908235
A46: 17058.697 | B46: 25873.352 | C46: 0.28922508 | D46: 4.24 | E46: 2.340392
A49: (d) Economic Discount Rate Sensitivity
A51: Economic Discount Rate | B51: ENPV (LKR mn) | C51: EIRR (%) | D51: EPBP (yrs) | E51: EBCR
A52: 9% (Base) | B52: =ENPV -> 28387.199 | C52: =EIRR -> 0.33947035 | D52: =DiscountedEPBP -> 3.53 | E52: =EBCR -> 2.6908235
A53: 0.07 | B53: 35002.86 | C53: 0.33947035 | D53: 3.37 | E53: 3.042943
A54: 0.09 | B54: 28387.199 | C54: 0.33947035 | D54: 3.53 | E54: 2.6908235
A55: 0.11 | B55: 23107.782 | C55: 0.33947035 | D55: 3.7 | E55: 2.398661
A58: (e) Social Cost of Carbon Sensitivity
A60: Social Cost of Carbon (LKR/ton) | B60: ENPV (LKR mn) | C60: EIRR (%) | D60: EPBP (yrs) | E60: EBCR
A61: 10000 (Base) | B61: =ENPV -> 28387.199 | C61: =EIRR -> 0.33947035 | D61: =DiscountedEPBP -> 3.53 | E61: =EBCR -> 2.6908235
A62: 5000 | B62: 21651.153 | C62: 0.28476441 | D62: 4.31 | E62: 2.2896052
A63: 10000 | B63: 28387.199 | C63: 0.33947035 | D63: 3.53 | E63: 2.6908235
A64: 15000 | B64: 35123.244 | C64: 0.39344722 | D64: 2.98 | E64: 3.0920418
A67: (f) SCF Sensitivity
A69: SCF | B69: ENPV (LKR mn) | C69: EIRR (%) | D69: EPBP (yrs) | E69: EBCR
A70: 0.9 (Base) | B70: =ENPV -> 28387.199 | C70: =EIRR -> 0.33947035 | D70: =DiscountedEPBP -> 3.53 | E70: =EBCR -> 2.6908235
A71: 0.85 | B71: 28658.522 | C71: 0.3454518 | D71: 3.46 | E71: 2.7350237
A72: 0.9 | B72: 28387.199 | C72: 0.33947035 | D72: 3.53 | E72: 2.6908235
A73: 0.95 | B73: 28115.875 | C73: 0.33366947 | D73: 3.6 | E73: 2.6480293
A76: (g) SWRF Sensitivity
A78: SWRF | B78: ENPV (LKR mn) | C78: EIRR (%) | D78: EPBP (yrs) | E78: EBCR
A79: 0.8 (Base) | B79: =ENPV -> 28387.199 | C79: =EIRR -> 0.33947035 | D79: =DiscountedEPBP -> 3.53 | E79: =EBCR -> 2.6908235
A80: 0.7 | B80: 28594.117 | C80: 0.34360851 | D80: 3.48 | E80: 2.7244009
A81: 0.8 | B81: 28387.199 | C81: 0.33947035 | D81: 3.53 | E81: 2.6908235
A82: 1 | B82: 27973.361 | C82: 0.33144022 | D82: 3.62 | E82: 2.6260921
A85: (h) SERF Sensitivity
A87: SERF | B87: ENPV (LKR mn) | C87: EIRR (%) | D87: EPBP (yrs) | E87: EBCR
A88: 1.1 (Base) | B88: =ENPV -> 28387.199 | C88: =EIRR -> 0.33947035 | D88: =DiscountedEPBP -> 3.53 | E88: =EBCR -> 2.6908235
A89: 1 | B89: 29316.272 | C89: 0.36350098 | D89: 3.26 | E89: 2.8484521
A90: 1.1 | B90: 28387.199 | C90: 0.33947035 | D90: 3.53 | E90: 2.6908235
A91: 1.2 | B91: 27458.125 | C91: 0.31824044 | D91: 3.79 | E91: 2.549726
A94: (i) O&M Sensitivity
A96: O&M % of CapEx | B96: ENPV (LKR mn) | C96: EIRR (%) | D96: EPBP (yrs) | E96: EBCR
A97: 1% (Base) | B97: =ENPV -> 28387.199 | C97: =EIRR -> 0.33947035 | D97: =DiscountedEPBP -> 3.53 | E97: =EBCR -> 2.6908235
A98: 0.0098 | B98: 28422.738 | C98: 0.33970205 | D98: 3.52 | E98: 2.6965317
A99: 0.01 | B99: 28387.199 | C99: 0.33947035 | D99: 3.53 | E99: 2.6908235
A100: 0.012 | B100: 28031.8 | C100: 0.33714997 | D100: 3.55 | E100: 2.6350435
A103: (j) O&M Escalation Sensitivity
A105: O&M Escalation | B105: ENPV (LKR mn) | C105: EIRR (%) | D105: EPBP (yrs) | E105: EBCR
A106: 5% (Base) | B106: =ENPV -> 28387.199 | C106: =EIRR -> 0.33947035 | D106: =DiscountedEPBP -> 3.53 | E106: =EBCR -> 2.6908235
A107: 0.03 | B107: 28639.444 | C107: 0.34019065 | D107: 3.52 | E107: 2.7318684
A108: 0.05 | B108: 28387.199 | C108: 0.33947035 | D108: 3.53 | E108: 2.6908235
A109: 0.07 | B109: 28075.084 | C109: 0.33865208 | D109: 3.53 | E109: 2.6417129
A112: (k) Employment at installation Sensitivity
A114: Employment at installation | B114: ENPV (LKR mn) | C114: EIRR (%) | D114: EPBP (yrs) | E114: EBCR
A115: 1000 (Base) | B115: =ENPV -> 28387.199 | C115: =EIRR -> 0.33947035 | D115: =DiscountedEPBP -> 3.53 | E115: =EBCR -> 2.6908235
A116: 800 | B116: 28187.199 | C116: 0.33453125 | D116: 3.59 | E116: 2.6789109
A117: 1000 | B117: 28387.199 | C117: 0.33947035 | D117: 3.53 | E117: 2.6908235
A118: 1200 | B118: 28587.199 | C118: 0.34454904 | D118: 3.47 | E118: 2.7027361
A121: (k) Employment after installation Sensitivity
A123: Employment after installation | B123: ENPV (LKR mn) | C123: EIRR (%) | D123: EPBP (yrs) | E123: EBCR
A124: 100 (Base) | B124: =ENPV -> 28387.199 | C124: =EIRR -> 0.33947035 | D124: =DiscountedEPBP -> 3.53 | E124: =EBCR -> 2.6908235
A125: 80 | B125: 28204.628 | C125: 0.33799915 | D125: 3.54 | E125: 2.6799491
A126: 100 | B126: 28387.199 | C126: 0.33947035 | D126: 3.53 | E126: 2.6908235
A127: 120 | B127: 28569.769 | C127: 0.34094103 | D127: 3.51 | E127: 2.701698
A130: (k) Employment income per yr Sensitivity
A132: Employment income/yr (LKR Mn) | B132: ENPV (LKR mn) | C132: EIRR (%) | D132: EPBP (yrs) | E132: EBCR
A133: 1 (Base) | B133: =ENPV -> 28387.199 | C133: =EIRR -> 0.33947035 | D133: =DiscountedEPBP -> 3.53 | E133: =EBCR -> 2.6908235
A134: 0.8 | B134: 28004.628 | C134: 0.33307937 | D134: 3.6 | E134: 2.6680365
A135: 1 | B135: 28387.199 | C135: 0.33947035 | D135: 3.53 | E135: 2.6908235
A136: 1.2 | B136: 28769.769 | C136: 0.34603964 | D136: 3.45 | E136: 2.7136105
A139: (j) Royalty Loss Sensitivity
A141: Royalty Loss (LKR Mn) | B141: ENPV (LKR mn) | C141: EIRR (%) | D141: EPBP (yrs) | E141: EBCR
A142: 15 (Base) | B142: =ENPV -> 28387.199 | C142: =EIRR -> 0.33947035 | D142: =DiscountedEPBP -> 3.53 | E142: =EBCR -> 2.6908235
A143: 7.5 | B143: 28387.199 | C143: 0.33947035 | D143: 3.53 | E143: 2.6908235
A144: 15 | B144: 28387.199 | C144: 0.33947035 | D144: 3.53 | E144: 2.6908235
A145: 22.5 | B145: 28387.199 | C145: 0.33947035 | D145: 3.53 | E145: 2.6908235
A148: (k) Environmental Impact Sensitivity
...
